setup.py
netdnarws/__init__.py
netdnarws/netdna.py
netdnarws.egg-info/PKG-INFO
netdnarws.egg-info/SOURCES.txt
netdnarws.egg-info/dependency_links.txt
netdnarws.egg-info/requires.txt
netdnarws.egg-info/top_level.txt