Metadata-Version: 1.0
Name: netdnarws
Version: 0.2.7
Summary: A Python REST Client for NetDNA REST Web Services
Home-page: http://developer.netdna.com
Author: NetDNA Developer Team
Author-email: devteam@netdna.com
License: GPL v3
Keywords: NetDNA CDN API REST
Platform: UNKNOWN
